certbot_dns_beget/__init__.py
certbot_dns_beget/dns_beget_api.py
certbot_dns_beget_api-1.0.1.dist-info/LICENSE
certbot_dns_beget_api-1.0.1.dist-info/METADATA
certbot_dns_beget_api-1.0.1.dist-info/WHEEL
certbot_dns_beget_api-1.0.1.dist-info/entry_points.txt
certbot_dns_beget_api-1.0.1.dist-info/top_level.txt
certbot_dns_beget_api-1.0.1.dist-info/RECORD
