Metadata-Version: 2.2
Name: certbot-dns-beget-api
Version: 1.0.1
Summary: Beget DNS plugin for Certbot
Home-page: https://github.com/Medan-rfz/certbot-dns-beget-api
Author: Medan-rfz
License: MIT License
License-File: LICENSE
Requires-Dist: certbot
Dynamic: author
Dynamic: description
Dynamic: description-content-type
Dynamic: home-page
Dynamic: license
Dynamic: requires-dist
Dynamic: summary
